mvtbdata/.DS_Store
mvtbdata/__init__.py
mvtbdata/mvtb_load_image_data.py
mvtbdata/__pycache__/__init__.cpython-38.pyc
mvtbdata/__pycache__/__init__.cpython-39.pyc
mvtbdata/__pycache__/mvtb_load_image_data.cpython-38.pyc
mvtbdata/data/D65.dat
mvtbdata/data/bb2.dat
mvtbdata/data/bunny.dat
mvtbdata/data/bunny.mat
mvtbdata/data/bunny.ply
mvtbdata/data/camera-2.dat
mvtbdata/data/cmfrgb.dat
mvtbdata/data/cmfxyz.dat
mvtbdata/data/cones.dat
mvtbdata/data/left_intrinsics.yml
mvtbdata/data/macbeth.dat
mvtbdata/data/peakfit.mat
mvtbdata/data/photopic.dat
mvtbdata/data/photopicluminosity.dat
mvtbdata/data/redbrick.dat
mvtbdata/data/rgb.txt
mvtbdata/data/scotopic.dat
mvtbdata/data/solar.dat
mvtbdata/data/water.dat
mvtbdata/images/.DS_Store
mvtbdata/images/58060.png
mvtbdata/images/5points.png
mvtbdata/images/Image18.png
mvtbdata/images/adelson.png
mvtbdata/images/apriltag12.png
mvtbdata/images/bouget.mat
mvtbdata/images/building2-1.png
mvtbdata/images/building2-2.png
mvtbdata/images/building2-3.png
mvtbdata/images/butterfly.jpg
mvtbdata/images/castle.png
mvtbdata/images/castle2.png
mvtbdata/images/church.jpg
mvtbdata/images/church.png
mvtbdata/images/eg-morph1.png
mvtbdata/images/eg-morph2.png
mvtbdata/images/eiffel-1.png
mvtbdata/images/eiffel-2.png
mvtbdata/images/fisheye_target.png
mvtbdata/images/flowers1.png
mvtbdata/images/flowers2.png
mvtbdata/images/flowers3.png
mvtbdata/images/flowers4.png
mvtbdata/images/flowers5.png
mvtbdata/images/flowers6.png
mvtbdata/images/flowers7.png
mvtbdata/images/flowers8.png
mvtbdata/images/flowers9.png
mvtbdata/images/greenscreen.png
mvtbdata/images/image0250_c0.pgm
mvtbdata/images/image3.jpg
mvtbdata/images/lab-scene.png
mvtbdata/images/lena.png
mvtbdata/images/monalisa.png
mvtbdata/images/multiblobs.png
mvtbdata/images/multiblobs_edgecase.png
mvtbdata/images/notre-dame.png
mvtbdata/images/parks.png
mvtbdata/images/penguins.png
mvtbdata/images/road.png
mvtbdata/images/rocks2-l.png
mvtbdata/images/rocks2-r.png
mvtbdata/images/roof.png
mvtb_data-1.4.dist-info/METADATA
mvtb_data-1.4.dist-info/WHEEL
mvtb_data-1.4.dist-info/top_level.txt
mvtb_data-1.4.dist-info/RECORD
