Metadata-Version: 2.1
Name: mvtb-data
Version: 1.4
Summary: Data files for the Machine Vision Toolbox for Python.
Home-page: https://github.com/petercorke/machinevision-toolbox-python
Author: Peter Corke
Author-email: rvc@petercorke.com
Project-URL: Source, https://github.com/petercorke/machinevision-toolbox-python
Keywords: python machine vision
Classifier: Development Status :: 5 - Production/Stable
Classifier: Intended Audience :: Developers
Classifier: License :: OSI Approved :: MIT License
Classifier: Programming Language :: Python :: 3 :: Only
